odoo/addons/account_statement_import_online_ofx/README.rst
odoo/addons/account_statement_import_online_ofx/__init__.py
odoo/addons/account_statement_import_online_ofx/__manifest__.py
odoo/addons/account_statement_import_online_ofx/i18n/account_statement_import_online_ofx.pot
odoo/addons/account_statement_import_online_ofx/i18n/it.po
odoo/addons/account_statement_import_online_ofx/models/__init__.py
odoo/addons/account_statement_import_online_ofx/models/ofx_institution.py
odoo/addons/account_statement_import_online_ofx/models/online_bank_statement_provider_ofx.py
odoo/addons/account_statement_import_online_ofx/readme/CONFIGURE.rst
odoo/addons/account_statement_import_online_ofx/readme/CONTRIBUTORS.rst
odoo/addons/account_statement_import_online_ofx/readme/DESCRIPTION.rst
odoo/addons/account_statement_import_online_ofx/readme/USAGE.rst
odoo/addons/account_statement_import_online_ofx/security/ir.model.access.csv
odoo/addons/account_statement_import_online_ofx/static/description/icon.png
odoo/addons/account_statement_import_online_ofx/static/description/index.html
odoo/addons/account_statement_import_online_ofx/tests/__init__.py
odoo/addons/account_statement_import_online_ofx/tests/test_account_statement_import_online_ofx.py
odoo/addons/account_statement_import_online_ofx/views/online_bank_statement_provider.xml
odoo/addons/account_statement_import_online_ofx/wizards/__init__.py
odoo/addons/account_statement_import_online_ofx/wizards/online_bank_statement_pull_wizard.py
odoo/addons/account_statement_import_online_ofx/wizards/online_bank_statement_pull_wizard.xml
odoo_addon_account_statement_import_online_ofx-16.0.1.0.0.3.dist-info/METADATA
odoo_addon_account_statement_import_online_ofx-16.0.1.0.0.3.dist-info/WHEEL
odoo_addon_account_statement_import_online_ofx-16.0.1.0.0.3.dist-info/top_level.txt
odoo_addon_account_statement_import_online_ofx-16.0.1.0.0.3.dist-info/RECORD
